LICENSE
MANIFEST.in
README-pypi.rst
README.md
pyproject.toml
requirements-dev.txt
requirements.txt
setup.cfg
setup.py
green/VERSION
green/__init__.py
green/__main__.py
green/cmdline.py
green/command.py
green/config.py
green/djangorunner.py
green/examples.py
green/exceptions.py
green/junit.py
green/loader.py
green/output.py
green/process.py
green/result.py
green/runner.py
green/shell_completion.sh
green/suite.py
green/version.py
green.egg-info/PKG-INFO
green.egg-info/SOURCES.txt
green.egg-info/dependency_links.txt
green.egg-info/entry_points.txt
green.egg-info/requires.txt
green.egg-info/top_level.txt
green/test/__init__.py
green/test/test_cmdline.py
green/test/test_command.py
green/test/test_config.py
green/test/test_djangorunner.py
green/test/test_integration.py
green/test/test_junit.py
green/test/test_load_tests.py
green/test/test_loader.py
green/test/test_output.py
green/test/test_process.py
green/test/test_result.py
green/test/test_runner.py
green/test/test_suite.py
green/test/test_version.py
green/test/test_windows.py