Metadata-Version: 2.1
Name: green
Version: 4.0.1
Summary: Green is a clean, colorful, fast python test runner.
Home-page: https://github.com/CleanCut/green
Author: Nathan Stocks
Author-email: nathan.stocks@gmail.com
Maintainer: Nathan Stocks
License: 'MIT'
Keywords: nose, nose2, trial, pytest, py.test, tox, green,,tdd, test, tests, functional, system, unit, unittest,,color, tabular, clean, red, rednose, regression, runner,,integration,smoke, white, black, box, incremental, end,,end-to-end, sanity, acceptance, load, stress, performance,,usability, install, uninstall, recovery, security,,comparison, alpha, beta, non-functional, destructive,,accessibility, internationalization, i18n, localization, l10n,,development, a/b, concurrent, conformance, veri
Classifier: Development Status :: 5 - Production/Stable
Classifier: Environment :: Console
Classifier: Intended Audience :: Developers
Classifier: License :: OSI Approved :: MIT License
Classifier: Natural Language :: English
Classifier: Operating System :: MacOS :: MacOS X
Classifier: Operating System :: Microsoft :: Windows
Classifier: Operating System :: POSIX
Classifier: Operating System :: POSIX :: Linux
Classifier: Operating System :: Unix
Classifier: Programming Language :: Python
Classifier: Programming Language :: Python :: 3
Classifier: Programming Language :: Python :: 3.8
Classifier: Programming Language :: Python :: 3.9
Classifier: Programming Language :: Python :: 3.10
Classifier: Programming Language :: Python :: 3.11
Classifier: Programming Language :: Python :: 3.12
Classifier: Programming Language :: Python :: 3 :: Only
Classifier: Topic :: Software Development :: Libraries
Classifier: Topic :: Software Development :: Quality Assurance
Classifier: Topic :: Software Development :: Testing
Classifier: Topic :: Utilities
Requires-Python: !=3.12.1,>=3.8
License-File: LICENSE
Requires-Dist: colorama
Requires-Dist: coverage
Requires-Dist: lxml
Requires-Dist: setuptools
Requires-Dist: unidecode
Provides-Extra: dev
Requires-Dist: black; extra == "dev"
Requires-Dist: coverage[toml]; python_full_version <= "3.11.0a6" and extra == "dev"
Requires-Dist: django; extra == "dev"
Requires-Dist: mypy; extra == "dev"
Requires-Dist: testtools; extra == "dev"
